Workbook

Sheet Cover & Legend
B2: GoBCB (rvl-etp) — Feature Matrix & BS-23 Verification Tracker
B3: Generated 2026-10-23 from docs/handover/feature-docs (English). The markdown docs remain the source of truth; regenerate with scripts/generate_feature_matrix.py — review entries are preserved.
B5: Purpose
B6: One readable overview of every feature of the event & ticketing platform for PM, QA, DEV, OPS and Head of Engineering, and the working document for the BS-23 verification review: confirm each feature, correct what is wrong, answer the 75 open queries, and log anything the documentation missed.
B8: How to use this workbook
B9: Role | C9: Where to look
B10: PM / HoE | C10: Summary sheet, then Feature Matrix filtered by Module or Area.
B11: QA | C11: Feature Matrix: 'What it does', 'Local testability', and defect-linked features (red 'Defect risk').
B12: DEV | C12: Traceability sheet (service, endpoint, state) and the 'Depends on / Affects' columns.
B13: OPS | C13: System-Initiated area, 'Deployment' open queries, Traceability 'External systems' column.
B14: BS-23 review session | C14: Feature Matrix status dropdown + comments → Open Queries responses → Gap Log.
B16: Evidence baseline (line numbers in the docs are valid for these commits)
B17: Repository | C17: Commit
B18: rvl-gobcb-backend | C18: 430ec16d7554254ff4f6adfa21f9c0c10d3234b2
B19: rvl-gobcb-admin-portal | C19: f62d2756bd9bbd4bfaa92585ae3f999d9f4c213f
B20: rvl-gobcb-user-portal | C20: 36aaf58c0dae070da9f958da09451d33e6e47c73
B21: rvl-gobcb-user-app | C21: 365b8bee71454d94747b75bef7cb07e8b47b6f8a
B22: rvl-gobcb-checker-app | C22: e919c54dad40a33aecc9922a68637a4a887513e6
B24: Numbers from the documentation
B25: Metric | C25: Value
B26: Feature files | C26: 103 (31 admin, 13 portal, 10 app, 6 checker, 17 system, 26 cross-cutting)
B27: Backend services | C27: 9 real + 2 stubs
B28: HTTP endpoints indexed | C28: 354 routes across 58 controllers
B29: Background workers | C29: 17
B30: SQS queues | C30: 6
B31: Open queries | C31: 75 (Q-01 … Q-77; Q-21 and Q-24 unused)
B32: Findings rated "defect" | C32: 23 — the ones to fix first
B34: Legend — Feature Matrix review status
B35: Status | C35: Meaning
B36: Not reviewed | C36: Default. Not yet checked with BS-23.
B37: Confirmed | C37: BS-23 confirms the documented feature is correct and complete.
B38: Correction needed | C38: BS-23 says the description is wrong — note the correction in the comments column.
B39: Missing detail | C39: Feature exists but a part of it is not documented.
B40: Not a feature | C40: Should not be tracked as a product feature (explain in comments).
B42: Legend — other columns
B43: Column | C43: Meaning
B44: Module | C44: RVL-defined functional tag for filtering (NOT part of the BS-23 docs).
B45: Defect risk | C45: Feature cites at least one open query of kind 'Defect' (code that appears wrong).
B46: Open queries | C46: Q-IDs this feature's doc cites as [UNCONFIRMED] — see the Open Queries sheet.
B47: Local testability | C47: From each doc's developer test guide: Full / Partial / Not locally.
B48: Query kinds | C48: External → BS23 answers · Deployment → BS23/infra · Ambiguity → BS23/business · Defect → RVL fixes.

Sheet Summary
B2: Summary — numbers & BS-23 verification progress
B4: Features by area & review progress (live counts from the Feature Matrix)
B5: Area | C5: Features | D5: With open queries | E5: Defect-linked | F5: Not reviewed | G5: Confirmed | H5: Correction needed | I5: Missing detail | J5: Not a feature
B6: Admin Portal | C6: 31 | D6: 16 | E6: 2 | F6: =COUNTIFS('Feature Matrix'!$B$5:$B$107,$B6,'Feature Matrix'!$Q$5:$Q$107,"Not reviewed") -> 31 | G6: =COUNTIFS('Feature Matrix'!$B$5:$B$107,$B6,'Feature Matrix'!$Q$5:$Q$107,"Confirmed") -> 0 | H6: =COUNTIFS('Feature Matrix'!$B$5:$B$107,$B6,'Feature Matrix'!$Q$5:$Q$107,"Correction needed") -> 0 | I6: =COUNTIFS('Feature Matrix'!$B$5:$B$107,$B6,'Feature Matrix'!$Q$5:$Q$107,"Missing detail") -> 0 | J6: =COUNTIFS('Feature Matrix'!$B$5:$B$107,$B6,'Feature Matrix'!$Q$5:$Q$107,"Not a feature") -> 0
B7: User Web Portal | C7: 13 | D7: 11 | E7: 3 | F7: =COUNTIFS('Feature Matrix'!$B$5:$B$107,$B7,'Feature Matrix'!$Q$5:$Q$107,"Not reviewed") -> 13 | G7: =COUNTIFS('Feature Matrix'!$B$5:$B$107,$B7,'Feature Matrix'!$Q$5:$Q$107,"Confirmed") -> 0 | H7: =COUNTIFS('Feature Matrix'!$B$5:$B$107,$B7,'Feature Matrix'!$Q$5:$Q$107,"Correction needed") -> 0 | I7: =COUNTIFS('Feature Matrix'!$B$5:$B$107,$B7,'Feature Matrix'!$Q$5:$Q$107,"Missing detail") -> 0 | J7: =COUNTIFS('Feature Matrix'!$B$5:$B$107,$B7,'Feature Matrix'!$Q$5:$Q$107,"Not a feature") -> 0
B8: User App | C8: 10 | D8: 10 | E8: 9 | F8: =COUNTIFS('Feature Matrix'!$B$5:$B$107,$B8,'Feature Matrix'!$Q$5:$Q$107,"Not reviewed") -> 10 | G8: =COUNTIFS('Feature Matrix'!$B$5:$B$107,$B8,'Feature Matrix'!$Q$5:$Q$107,"Confirmed") -> 0 | H8: =COUNTIFS('Feature Matrix'!$B$5:$B$107,$B8,'Feature Matrix'!$Q$5:$Q$107,"Correction needed") -> 0 | I8: =COUNTIFS('Feature Matrix'!$B$5:$B$107,$B8,'Feature Matrix'!$Q$5:$Q$107,"Missing detail") -> 0 | J8: =COUNTIFS('Feature Matrix'!$B$5:$B$107,$B8,'Feature Matrix'!$Q$5:$Q$107,"Not a feature") -> 0
B9: Checker App | C9: 6 | D9: 6 | E9: 5 | F9: =COUNTIFS('Feature Matrix'!$B$5:$B$107,$B9,'Feature Matrix'!$Q$5:$Q$107,"Not reviewed") -> 6 | G9: =COUNTIFS('Feature Matrix'!$B$5:$B$107,$B9,'Feature Matrix'!$Q$5:$Q$107,"Confirmed") -> 0 | H9: =COUNTIFS('Feature Matrix'!$B$5:$B$107,$B9,'Feature Matrix'!$Q$5:$Q$107,"Correction needed") -> 0 | I9: =COUNTIFS('Feature Matrix'!$B$5:$B$107,$B9,'Feature Matrix'!$Q$5:$Q$107,"Missing detail") -> 0 | J9: =COUNTIFS('Feature Matrix'!$B$5:$B$107,$B9,'Feature Matrix'!$Q$5:$Q$107,"Not a feature") -> 0
B10: System-Initiated | C10: 17 | D10: 14 | E10: 4 | F10: =COUNTIFS('Feature Matrix'!$B$5:$B$107,$B10,'Feature Matrix'!$Q$5:$Q$107,"Not reviewed") -> 17 | G10: =COUNTIFS('Feature Matrix'!$B$5:$B$107,$B10,'Feature Matrix'!$Q$5:$Q$107,"Confirmed") -> 0 | H10: =COUNTIFS('Feature Matrix'!$B$5:$B$107,$B10,'Feature Matrix'!$Q$5:$Q$107,"Correction needed") -> 0 | I10: =COUNTIFS('Feature Matrix'!$B$5:$B$107,$B10,'Feature Matrix'!$Q$5:$Q$107,"Missing detail") -> 0 | J10: =COUNTIFS('Feature Matrix'!$B$5:$B$107,$B10,'Feature Matrix'!$Q$5:$Q$107,"Not a feature") -> 0
B11: Cross-Cutting | C11: 26 | D11: 19 | E11: 0 | F11: =COUNTIFS('Feature Matrix'!$B$5:$B$107,$B11,'Feature Matrix'!$Q$5:$Q$107,"Not reviewed") -> 26 | G11: =COUNTIFS('Feature Matrix'!$B$5:$B$107,$B11,'Feature Matrix'!$Q$5:$Q$107,"Confirmed") -> 0 | H11: =COUNTIFS('Feature Matrix'!$B$5:$B$107,$B11,'Feature Matrix'!$Q$5:$Q$107,"Correction needed") -> 0 | I11: =COUNTIFS('Feature Matrix'!$B$5:$B$107,$B11,'Feature Matrix'!$Q$5:$Q$107,"Missing detail") -> 0 | J11: =COUNTIFS('Feature Matrix'!$B$5:$B$107,$B11,'Feature Matrix'!$Q$5:$Q$107,"Not a feature") -> 0
B12: Total | C12: =SUM(C6:C11) -> 103 | D12: =SUM(D6:D11) -> 76 | E12: =SUM(E6:E11) -> 23 | F12: =SUM(F6:F11) -> 103 | G12: =SUM(G6:G11) -> 0 | H12: =SUM(H6:H11) -> 0 | I12: =SUM(I6:I11) -> 0 | J12: =SUM(J6:J11) -> 0
B15: Open queries by kind & answer status (live counts from the Open Queries sheet)
B16: Kind | C16: Count | D16: Who answers | E16: Open | F16: Answered - accepted | G16: Answered - disputed | H16: N/A
B17: External | C17: 10 | D17: BS23 | E17: =COUNTIFS('Open Queries'!$C$5:$C$79,$B17,'Open Queries'!$H$5:$H$79,"Open") -> 10 | F17: =COUNTIFS('Open Queries'!$C$5:$C$79,$B17,'Open Queries'!$H$5:$H$79,"Answered - accepted") -> 0 | G17: =COUNTIFS('Open Queries'!$C$5:$C$79,$B17,'Open Queries'!$H$5:$H$79,"Answered - disputed") -> 0 | H17: =COUNTIFS('Open Queries'!$C$5:$C$79,$B17,'Open Queries'!$H$5:$H$79,"N/A") -> 0
B18: Deployment | C18: 15 | D18: BS23 / infrastructure | E18: =COUNTIFS('Open Queries'!$C$5:$C$79,$B18,'Open Queries'!$H$5:$H$79,"Open") -> 15 | F18: =COUNTIFS('Open Queries'!$C$5:$C$79,$B18,'Open Queries'!$H$5:$H$79,"Answered - accepted") -> 0 | G18: =COUNTIFS('Open Queries'!$C$5:$C$79,$B18,'Open Queries'!$H$5:$H$79,"Answered - disputed") -> 0 | H18: =COUNTIFS('Open Queries'!$C$5:$C$79,$B18,'Open Queries'!$H$5:$H$79,"N/A") -> 0
B19: Ambiguity | C19: 27 | D19: BS23 / the business | E19: =COUNTIFS('Open Queries'!$C$5:$C$79,$B19,'Open Queries'!$H$5:$H$79,"Open") -> 27 | F19: =COUNTIFS('Open Queries'!$C$5:$C$79,$B19,'Open Queries'!$H$5:$H$79,"Answered - accepted") -> 0 | G19: =COUNTIFS('Open Queries'!$C$5:$C$79,$B19,'Open Queries'!$H$5:$H$79,"Answered - disputed") -> 0 | H19: =COUNTIFS('Open Queries'!$C$5:$C$79,$B19,'Open Queries'!$H$5:$H$79,"N/A") -> 0
B20: Defect | C20: 23 | D20: RVL (finding to fix) | E20: =COUNTIFS('Open Queries'!$C$5:$C$79,$B20,'Open Queries'!$H$5:$H$79,"Open") -> 23 | F20: =COUNTIFS('Open Queries'!$C$5:$C$79,$B20,'Open Queries'!$H$5:$H$79,"Answered - accepted") -> 0 | G20: =COUNTIFS('Open Queries'!$C$5:$C$79,$B20,'Open Queries'!$H$5:$H$79,"Answered - disputed") -> 0 | H20: =COUNTIFS('Open Queries'!$C$5:$C$79,$B20,'Open Queries'!$H$5:$H$79,"N/A") -> 0
B21: Total | C21: =SUM(C17:C20) -> 75 | E21: =SUM(E17:E20) -> 75 | F21: =SUM(F17:F20) -> 0 | G21: =SUM(G17:G20) -> 0 | H21: =SUM(H17:H20) -> 0
B24: Local testability (from each doc's developer test guide)
B25: Rating | C25: Features
B26: Full | C26: 64
B27: Partial | C27: 32
B28: Not locally | C28: 7
B29: Mixed / other | C29: 0

Sheet Feature Matrix
B2: Feature Matrix — all 103 features, grouped by area
B3: One row per feature doc (docs/handover/feature-docs). Columns A–O are generated from the docs; columns P–Q are the BS-23 review. Module is an RVL-defined functional tag.
B4: Area | C4: Module | D4: ID | E4: Feature | F4: What it does | G4: Who starts it | H4: Service(s) | I4: Endpoints | J4: Primary endpoint | K4: Depends on | L4: Affects | M4: Open queries | N4: Defect risk | O4: Local testability | P4: Doc | Q4: BS-23 status | R4: BS-23 comments / corrections
B5: Admin Portal | C5: Programs & Events | D5: A-01 | E5: Program selection and program-scoped menu | F5: Pick a program (series/tournament); the portal then sends X-Program-Id and shows the program menu. | G5: Any signed-in staff member (admin pool; roles admin, event_manager, ticket_manager, ticket_operator, customer_support, ticket_operator (BCBPersonnel), X-15). | H5: Admin | I5: 1 | J5: GET /admin/api/v1/program | K5: A-02, X-01, X-15 | L5: A-07, A-15, A-21, A-22 | M5: — | N5: — | O5: Full | P5: feature-docs/en/10-admin-portal/A-01-program-selection.md | Q5: Not reviewed
B6: Admin Portal | C6: Programs & Events | D6: A-02 | E6: Programs | F6: Create, edit and delete programs (a series or tournament that groups events). | G6: Staff signed in to the admin portal with the roles allowed on ProgramController (admin, event_manager, ticket_manager, customer_support, ticket_operator (BCBPersonnel) can read; see §9 for who can write). | H6: Admin | I6: 5 | J6: POST /admin/api/v1/program | K6: X-01, X-15 | L6: A-03, A-04, A-06, A-07, A-13, A-15, A-16, A-25 | M6: — | N6: — | O6: Full | P6: feature-docs/en/10-admin-portal/A-02-programs.md | Q6: Not reviewed
B7: Admin Portal | C7: Programs & Events | D7: A-03 | E7: Program settings | F7: Per-program commercial rules: payment gateway, purchase limits, VAT/service charge, ticket prefix. | G7: Staff with role admin or event_manager (the controller allows only these two). | H7: Admin | I7: 3 | J7: /admin/api/v1/program-settings | K7: A-02 | L7: A-07, A-08, P-04, P-06, S-07, S-10 | M7: Q-19 | N7: — | O7: Full | P7: feature-docs/en/10-admin-portal/A-03-program-settings.md | Q7: Not reviewed
B8: Admin Portal | C8: Programs & Events | D8: A-04 | E8: Teams | F8: Maintain the teams that play in a program's events. | G8: Staff with role admin or event_manager (TeamsController). | H8: Admin | I8: 7 | J8: /admin/api/v1/teams | K8: A-02 | L8: A-07, P-02, U-02 | M8: Q-20 | N8: — | O8: Full | P8: feature-docs/en/10-admin-portal/A-04-teams.md | Q8: Not reviewed
B9: Admin Portal | C9: Venues & Seating | D9: A-05 | E9: Venues and stadium layout | F9: Define a venue: SVG map, gallery → block → level hierarchy, entry gates and mini gates. | G9: Staff with role admin or event_manager (VenuesController). | H9: Admin | I9: 8 | J9: /admin/api/v1/venues | K9: X-15 | L9: A-06, A-07, A-09, A-10, A-11, A-18, P-04, S-07 | M9: — | N9: — | O9: Full | P9: feature-docs/en/10-admin-portal/A-05-venues.md | Q9: Not reviewed
B10: Admin Portal | C10: Venues & Seating | D10: A-06 | E10: Program–venue mapping and venue details | F10: Attach venues to a program and generate/sync the per-program venue details (price, capacity, currency per level). | G10: Staff with role admin or event_manager (ProgramVenueController, ProgramVenueDetailsController). | H10: Admin | I10: 9 | J10: /admin/api/v1/programVenueDetails | K10: A-02, A-05 | L10: A-07, A-09, A-13 | M10: — | N10: — | O10: Full | P10: feature-docs/en/10-admin-portal/A-06-program-venue-mapping.md | Q10: Not reviewed
B11: Admin Portal | C11: Programs & Events | D11: A-07 | E11: Events (matches) | F11: Create, edit, segment, publish/unpublish, duplicate and enable/disable events. | G11: Staff with roles admin, event_manager, ticket_manager, ticket_operator (BCBPersonnel) (class attribute of EventsController; [AuthorizeProgram] is commented out). | H11: Admin | I11: 8 | J11: /admin/api/v1/events | K11: A-02, A-03, A-04, A-05, A-06, A-13 | L11: A-08, A-12, P-02, P-04, P-06, S-07 | M11: — | N11: — | O11: Full | P11: feature-docs/en/10-admin-portal/A-07-events.md | Q11: Not reviewed
B12: Admin Portal | C12: Programs & Events | D12: A-08 | E12: Event settings override | F12: Override program settings for a single event. | G12: Staff who can open the event details page (/events/event-details/:id), tab Event Settings. | H12: Admin | I12: 2 | J12: /admin/api/v1/event-settings | K12: A-03, A-07 | L12: P-06, S-07, S-10 | M12: — | N12: — | O12: Full | P12: feature-docs/en/10-admin-portal/A-08-event-settings.md | Q12: Not reviewed
B13: Admin Portal | C13: Pricing & Promotions | D13: A-09 | E13: Event venue details and per-level pricing | F13: View an event's venue tree and change the price of a level. | G13: Staff with roles admin, event_manager, ticket_manager, ticket_operator (BCBPersonnel) (EventsVenueDetailsController). | H13: Admin | I13: 5 | J13: /admin/api/v1/eventsVenueDetails | K13: A-06, A-07 | L13: A-22, P-04, P-06, S-10 | M13: — | N13: — | O13: Full | P13: feature-docs/en/10-admin-portal/A-09-event-level-pricing.md | Q13: Not reviewed
B14: Admin Portal | C14: Venues & Seating | D14: A-10 | E14: Event capacity adjustment | F14: Increase or decrease the sellable capacity of a level for an event. | G14: Staff on the event's Gallery Update tab (/events/event-details/:id), columns "Remaining Allocated" and "De-allocated". | H14: Booking | I14: 4 | J14: /booking/api/v1/event-capacity-adjustment | K14: A-07, A-09 | L14: A-11, A-21, P-04, S-01, S-02 | M14: — | N14: — | O14: Full | P14: feature-docs/en/10-admin-portal/A-10-capacity-adjustment.md | Q14: Not reviewed
B15: Admin Portal | C15: Ticketing | D15: A-11 | E15: Seat reservation (complimentary / partner) | F15: Hold seats outside online sale for complimentary or partner use. | G15: Staff on the event's Gallery Update tab (/events/event-details/:id, columns "Remaining Reserved" and "Released") and the Generate Tickets menu (/events/event-ticket, /events/generate-ticket/:id). | H15: Booking | I15: 5 | J15: /booking/api/v1/seat-reservation | K15: A-07, A-09 | L15: A-12, P-04, S-01, S-09 | M15: Q-22 | N15: — | O15: Full | P15: feature-docs/en/10-admin-portal/A-11-seat-reservation.md | Q15: Not reviewed
B16: Admin Portal | C16: Ticketing | D16: A-12 | E16: Reserved ticket generation and distribution | F16: Generate, sign, merge/zip, download and email the tickets of a reservation ("Generate Tickets" menu). | G16: Staff with the admin policy (Ticketing [Authorize(Policy = Admin)] on every endpoint here). | H16: Booking, Ticketing | I16: 9 | J16: /booking/api/v1/seat-reservation | K16: A-11, A-13, X-20 | L16: C-02, S-08, S-09, X-21 | M16: — | N16: — | O16: Partial | P16: feature-docs/en/10-admin-portal/A-12-reserved-tickets.md | Q16: Not reviewed
... B30: Admin Portal | C30: Users & Accounts | D30: A-26 | E30: Agent (seller) users | F30: Manage the Agent-pool accounts of offline seller agents. | G30: Staff in the global menu (Users → Seller Agents, /agent-user, program 0). | H30: Admin | I30: 5 | J30: /admin/api/v1/agent-users | K30: X-05 | L30: X-13 | M30: Q-07 | N30: — | O30: Partial | P30: feature-docs/en/10-admin-portal/A-26-agent-users.md | Q30: Not reviewed
B31: Admin Portal | C31: Auth & Security | D31: A-27 | E31: Activity log viewer | F31: Browse the audit trail of changes made through the services. | G31: - Global log: /activity-log (global menu, AuthGuard; the menu shows it in the admin's global menu). | H31: Admin | I31: — | J31: /admin/api/v1/activity-log | K31: X-24 | L31: nothing. | M31: — | N31: — | O31: Full | P31: feature-docs/en/10-admin-portal/A-27-activity-log.md | Q31: Not reviewed
B32: Admin Portal | C32: Content & CMS | D32: A-28 | E32: Media configuration (banners, gallery, contact, registration) | F32: Manage the images and blocks shown on the public portal and app. | G32: Staff who can open Site Settings → Media Configuration (global menu, /media-configuration; no route guard beyond sign-in). | H32: Admin | I32: 6 | J32: /admin/api/v1/landing-page-image | K32: X-01 | L32: P-01, P-03, U-02 | M32: — | N32: — | O32: Full | P32: feature-docs/en/10-admin-portal/A-28-media-configuration.md | Q32: Not reviewed
B33: Admin Portal | C33: Content & CMS | D33: A-29 | E33: Content editor (T&C, FAQ, privacy, notice) | F33: Edit the static content pages shown to customers. | G33: Staff who can open Site Settings → Content Editor (global menu, /content-editor, tabs terms-conditions (default), faq, privacy-policy, ticket-pricing, notice). | H33: Admin | I33: — | J33: Redis-published content (no endpoint) | K33: A-28 | L33: P-03, U-03 | M33: Q-33, Q-35 | N33: Yes (1) | O33: Full | P33: feature-docs/en/10-admin-portal/A-29-content-editor.md | Q33: Not reviewed
B34: Admin Portal | C34: Content & CMS | D34: A-30 | E34: Header/footer and social-media settings | F34: Edit the public header/footer and the social-media links. | G34: - Header/footer: staff in Site Settings → Media Configuration (page section HeaderFooterComponent). | H34: Admin | I34: 4 | J34: /admin/api/v1/header-footer | K34: nothing. | L34: P-01, U-02 | M34: Q-34 | N34: — | O34: Full | P34: feature-docs/en/10-admin-portal/A-30-header-footer-social.md | Q34: Not reviewed
B35: Admin Portal | C35: Content & CMS | D35: A-31 | E35: General notices | F35: Publish notices that the public portal shows. | G35: Staff on /settings/notice (the program-settings module; not linked from any menu, reachable only by URL). | H35: Admin | I35: 5 | J35: /admin/api/v1/general-notice | K35: A-02 | L35: P-03 | M35: Q-33, Q-35 | N35: Yes (1) | O35: Full | P35: feature-docs/en/10-admin-portal/A-31-general-notices.md | Q35: Not reviewed
B36: User Web Portal | C36: Content & CMS | D36: P-01 | E36: Home page content | F36: Banners, header/footer, notices and program list on the landing page. | G36: Any visitor, no sign-in (the home route has no guard). | H36: Event, Admin | I36: 4 | J36: GET /event/api/v1/landing-page-image/public | K36: A-28, A-29, A-30 | L36: P-02, P-03 | M36: Q-04, Q-34, Q-35 | N36: — | O36: Full | P36: feature-docs/en/20-user-portal/P-01-home-content.md | Q36: Not reviewed
B37: User Web Portal | C37: Programs & Events | D37: P-02 | E37: Browse events and event details | F37: Event lists and the event detail page. | G37: Any visitor for browsing (no sign-in). Pressing Buy tickets needs a signed-in customer with a completed profile. | H37: Event | I37: 3 | J37: GET /event/api/v1/events/list | K37: A-07, A-09, S-02 | L37: P-04 | M37: Q-36 | N37: — | O37: Full | P37: feature-docs/en/20-user-portal/P-02-browse-events.md | Q37: Not reviewed
B38: User Web Portal | C38: Content & CMS | D38: P-03 | E38: Information pages (pricing, gallery, contact, policies) | F38: Ticket-pricing, gallery, contact, terms, privacy, FAQ and ICC code pages. | G38: Any visitor, no sign-in. Routes (all under /{lang}/): ticket-pricing, gallery, faq, terms, policy, contact, message-sent, icc-anti-racism-code, icc-anti-discrimination-code (event-routing. | H38: Event | I38: 2 | J38: GET /event/api/v1/ticket-pricing/program-pricing | K38: A-09, A-28, A-29, A-30, P-01 | L38: nothing downstream. | M38: Q-33, Q-35 | N38: Yes (1) | O38: Full | P38: feature-docs/en/20-user-portal/P-03-info-pages.md | Q38: Not reviewed
B39: User Web Portal | C39: Bookings & Payments | D39: P-04 | E39: Seat selection | F39: Stadium map, live availability, seat/quantity choice and automatic discount. | G39: Signed-in customer (User pool). Route /{lang}/tickets/{eventId}/seats, protected by AuthGuard (local flag only, X-10) and by a route resolver (VenueDetailsResolverService). | H39: Booking | I39: 3 | J39: GET /booking/api/v1/capacity/level-user-portal-seats | K39: A-09, A-10, A-11, A-16, P-02, S-01 | L39: P-05, P-06 | M39: — | N39: — | O39: Full | P39: feature-docs/en/20-user-portal/P-04-seat-selection.md | Q39: Not reviewed
B40: User Web Portal | C40: Pricing & Promotions | D40: P-05 | E40: Apply promo code | F40: Validate a promo code before checkout and show the discount. | G40: Signed-in customer on /{lang}/tickets/{eventId}/seats. | H40: Booking | I40: 1 | J40: /booking/api/v1/user-booking-order (apply step) | K40: A-15, P-04 | L40: A-22, P-06 | M40: Q-18, Q-37 | N40: — | O40: Full | P40: feature-docs/en/20-user-portal/P-05-apply-promo-code.md | Q40: Not reviewed
B41: User Web Portal | C41: Bookings & Payments | D41: P-06 | E41: Booking order and online payment (DgePay) | F41: Create the order, lock capacity, pay through DgePay and handle the callback. | G41: Signed-in customer with a completed profile (the server refuses otherwise), pressing Purchase on the seats page and confirming in the payment pop-up (CompletePaymentModalComponent). | H41: Booking | I41: 3 | J41: POST /booking/api/v1/user-booking-order | K41: A-03, A-08, A-16, P-04, P-05, X-06 | L41: A-22, A-23, P-07, P-08, S-01, S-05, S-07, S-10 | M41: Q-11, Q-15, Q-37, Q-38, Q-39 | N41: — | O41: Partial | P41: feature-docs/en/20-user-portal/P-06-booking-payment.md | Q41: Not reviewed
B42: User Web Portal | C42: Bookings & Payments | D42: P-07 | E42: My bookings and generation status | F42: List the customer's orders and poll until tickets are generated. | G42: Signed-in customer. Route /{lang}/tickets (AllBookingsPageComponent, AuthGuard). | H42: Booking | I42: 1 | J42: /booking/api/v1/user-booking-order (list) | K42: P-06 | L42: P-09, P-10, P-12 | M42: — | N42: — | O42: Full | P42: feature-docs/en/20-user-portal/P-07-my-bookings.md | Q42: Not reviewed
B43: User Web Portal | C43: Ticketing | D43: P-08 | E43: Ticket generation request | F43: Ask the platform to generate the tickets of a paid order. | G43: Signed-in customer on /{lang}/tickets/ticket-details/{publicId} (TicketPreviewComponent), only when the order is Paid and the event's ticketAvailabilityStartDateTime has passed (holder names and phones are filled in bef… | H43: Ticketing | I43: 3 | J43: PATCH /ticketing/api/v1/booking-order-ticket/generate-request/{id} | K43: A-07, A-13, P-06, P-09 | L43: P-09, S-06, S-08, S-12 | M43: Q-12, Q-40 | N43: — | O43: Partial | P43: feature-docs/en/20-user-portal/P-08-ticket-generation-request.md | Q43: Not reviewed
B44: User Web Portal | C44: Ticketing | D44: P-09 | E44: Ticket details, holder info, download, share, invoice | F44: View tickets, edit the holder, download one/all, share a link, download the invoice. | G44: Signed-in customer who owns the order. Routes /{lang}/tickets/ticket-details/{publicId} and /{lang}/tickets/payment-invoice/{publicId} (both BookingDetailsComponent; the invoice route only switches the view mode). | H44: Ticketing | I44: 7 | J44: /ticketing/api/v1/booking-order-ticket | K44: P-06, P-08, S-08 | L44: C-02, P-10 | M44: Q-41 | N44: — | O44: Partial | P44: feature-docs/en/20-user-portal/P-09-ticket-details-downloads.md | Q44: Not reviewed
B45: User Web Portal | C45: Ticketing | D45: P-10 | E45: Sync tickets to OneID wallet | F45: Push a ticket or a whole order to the customer's OneID wallet. | G45: Signed-in customer whose profile sso_provider is oneid, on the ticket page of a Generated order (P-09); the button shows only while not all tickets are synced. | H45: Ticketing | I45: 2 | J45: …/sync-order-to-oneid | K45: P-08, S-08, X-08 | L45: P-07 | M45: Q-06, Q-41 | N45: — | O45: Not locally | P45: feature-docs/en/20-user-portal/P-10-oneid-ticket-sync.md | Q45: Not reviewed
... B47: User Web Portal | C47: Support & Issues | D47: P-12 | E47: Report an issue and chat with support | F47: Raise an issue about an order and chat with support in real time. | G47: Customer on /en/issues, a route that does have AuthGuard (app-routing.module.ts:25-31). | H47: UserIssue | I47: 7 | J47: POST /userissue/api/v1/user-issue, SignalR hub | K47: A-02, P-07, P-11 | L47: A-24 | M47: Q-46, Q-47, Q-48, Q-49, Q-50 | N47: Yes (2) | O47: Full for issues and REST chat; Partial… | P47: feature-docs/en/20-user-portal/P-12-issues-chat.md | Q47: Not reviewed
B48: User Web Portal | C48: Content & CMS | D48: P-13 | E48: Language switch (EN/BN) | F48: Switch the portal language through the /:lang route segment. | G48: Any visitor, signed in or not. Control: the flag dropdown in the toolbar, available in both the desktop and mobile layouts (layout/components/toolbar/toolbar. | H48: — (client only) | I48: — | J48: — | K48: nothing in the backend. | L48: P-01, P-02, P-03, P-04, P-07, P-11, P-12 | M48: Q-44, Q-45 | N48: Yes (1) | O48: Full | P48: feature-docs/en/20-user-portal/P-13-language-switch.md | Q48: Not reviewed
B49: User App | C49: Platform & Infrastructure | D49: U-01 | E49: Splash, version gate and onboarding | F49: Start-up: env check, force-update check, onboarding, session restore. | G49: Every cold start. Route /splash (RoutePath. | H49: Identity API (external) | I49: 1 | J49: GET user/allowed-app-version | K49: X-11 | L49: everything — every other U-xx entry starts from the session… | M49: Q-01, Q-51, Q-52 | N49: Yes (1) | O49: Full | P49: feature-docs/en/30-user-app/U-01-splash-onboarding.md | Q49: Not reviewed
B50: User App | C50: Programs & Events | D50: U-02 | E50: Home and browse events | F50: Home content, event list and event details in the app. | G50: Signed-in customer. Home is only reachable from U-01 when a session exists. | H50: Event | I50: 7 | J50: /event/api/v1/… | K50: A-07, A-09, A-28, U-01 | L50: U-04, U-05 | M50: Q-53, Q-54 | N50: Yes (2) | O50: Full | P50: feature-docs/en/30-user-app/U-02-home-browse-events.md | Q50: Not reviewed
B51: User App | C51: Content & CMS | D51: U-03 | E51: Information pages (pricing, gallery, contact) | F51: Ticket pricing, gallery and contact screens. | G51: Signed-in customer. Routes /ticketPricing, /gallery, /contact. | H51: Event | I51: 3 | J51: /event/api/v1/… | K51: A-09, A-28, A-30, U-02 | L51: nothing downstream — all three screens are terminal reads. | M51: Q-53, Q-55 | N51: Yes (2) | O51: Full | P51: feature-docs/en/30-user-app/U-03-info-pages.md | Q51: Not reviewed
B52: User App | C52: Bookings & Payments | D52: U-04 | E52: Seat selection and promo code | F52: Choose seats/quantity, see discounts, apply a promo code. | G52: Signed-in customer, from the event details screen (U-02). | H52: Booking, Admin (discounts) | I52: 4 | J52: /booking/api/v1/capacity/…, /admin/api/v1/discount/program/… | K52: A-10, A-15, A-16, U-02 | L52: S-01, U-05 | M52: Q-54, Q-56, Q-57 | N52: Yes (1) | O52: Full | P52: feature-docs/en/30-user-app/U-04-seat-selection-promo.md | Q52: Not reviewed
B53: User App | C53: Bookings & Payments | D53: U-05 | E53: Booking and WebView payment | F53: Create the order and pay in an in-app WebView; success is detected from the URL. | G53: Signed-in customer completing U-04. Route /payment (RoutePath. | H53: Booking | I53: 1 | J53: POST /booking/api/v1/user-booking-order, DgePay WebView | K53: A-03, U-04, X-19 | L53: S-01, S-05, U-06 | M53: Q-57, Q-58, Q-59 | N53: Yes (1) | O53: Partial | P53: feature-docs/en/30-user-app/U-05-booking-webview-payment.md | Q53: Not reviewed
B54: User App | C54: Bookings & Payments | D54: U-06 | E54: My bookings and tickets | F54: Order list, booking details, ticket actions (holder edit, download, share, OneID sync). | G54: Signed-in customer. Routes /bookingList, /bookingDetails, /paymentDetails. | H54: Booking, Ticketing | I54: 10 | J54: /booking/api/v1/user-booking-order/…, /ticketing/api/v1/booking-order-ticket | K54: S-06, S-07, U-05 | L54: C-02 | M54: Q-54 | N54: Yes (1) | O54: Full | P54: feature-docs/en/30-user-app/U-06-my-bookings-tickets.md | Q54: Not reviewed
B55: User App | C55: Users & Accounts | D55: U-07 | E55: Profile and settings | F55: Profile view/update, language, logout and delete-account entry. | G55: Signed-in customer, from the Home drawer or profile tab. | H55: Identity API (external) | I55: 4 | J55: GET user/my-profile?user_id=… | K55: X-06, X-07, X-08 | L55: U-09 | M55: Q-01, Q-43, Q-60, Q-61 | N55: Yes (2) | O55: Partial | P55: feature-docs/en/30-user-app/U-07-profile-settings.md | Q55: Not reviewed
B56: User App | C56: Support & Issues | D56: U-08 | E56: Report an issue and support chat | F56: Raise issues and exchange messages with support. | G56: Signed-in customer. Routes /issues (list), /reportIssue (raise), /chatCommunication (thread). | H56: UserIssue | I56: 6 | J56: /userissue/api/v1/user-issue, SignalR + REST fallback | K56: U-06, U-07 | L56: A-24 | M56: Q-46, Q-48 | N56: Yes (1) | O56: Full | P56: feature-docs/en/30-user-app/U-08-issues-chat.md | Q56: Not reviewed
B57: User App | C57: Notifications | D57: U-09 | E57: Push device-token registration | F57: Register/refresh the FCM token of the device with the PushNotification service. | G57: Any signed-in customer, once per token value. | H57: PushNotification | I57: 3 | J57: /pushnotification/api/v1/device-token | K57: U-07, X-07 | L57: S-11, S-12, S-13, U-10 | M57: Q-62, Q-63 | N57: — | O57: Partial | P57: feature-docs/en/30-user-app/U-09-device-token.md | Q57: Not reviewed
B58: User App | C58: Notifications | D58: U-10 | E58: Receiving push notifications | F58: How the app receives and opens push messages (event published, ticket generated). | G58: Any signed-in customer with a registered device token (U-09). | H58: — (Firebase SDK) | I58: — | J58: — (Firebase SDK only) | K58: S-11, S-12, U-09 | L58: U-06 | M58: Q-64, Q-65 | N58: Yes (2) | O58: Not locally | P58: feature-docs/en/30-user-app/U-10-push-receipt.md | Q58: Not reviewed
B59: Checker App | C59: Gate Operations & Checking | D59: C-01 | E59: Assigned event and gate | F59: Load the event and gate the checker is assigned to. | G59: A ticket checker in the TicketChecker Cognito pool (X-12). | H59: Admin | I59: 1 | J59: GET /admin/api/v1/ticket-checker-gate/event-info | K59: A-17, A-18, X-12 | L59: C-02, C-03, C-05 | M59: Q-66, Q-67 | N59: — | O59: Full | P59: feature-docs/en/40-checker-app/C-01-assigned-event-gate.md | Q59: Not reviewed
B60: Checker App | C60: Gate Operations & Checking | D60: C-02 | E60: Ticket download for offline checking | F60: Download the gate's valid tickets into the device database. | G60: A checker at C-01 with a known event and gate. | H60: TicketChecker | I60: 1 | J60: POST /ticketChecker/api/v1/tickets/sync-tickets | K60: A-19, C-01 | L60: C-03, C-04, C-05 | M60: Q-68, Q-69, Q-70 | N60: Yes (1) | O60: Full | P60: feature-docs/en/40-checker-app/C-02-offline-ticket-download.md | Q60: Not reviewed
B61: Checker App | C61: Gate Operations & Checking | D61: C-03 | E61: QR scan validation | F61: Scan a ticket QR, verify signature, gate and event offline, mark it used. | G61: A checker at the gate, route /qrPage. | H61: none (local crypto) | I61: — | J61: — (Method channel certificate/methods) | K61: A-13, C-01, C-02, S-08 | L61: A-19, C-05 | M61: Q-71, Q-72, Q-73, Q-74 | N61: Yes (3) | O61: Full on Android; Not locally on iOS | P61: feature-docs/en/40-checker-app/C-03-qr-scan-validation.md | Q61: Not reviewed
B62: Checker App | C62: Gate Operations & Checking | D62: C-04 | E62: Manual entry | F62: Admit a ticket by typing its number when the QR cannot be read. | G62: A checker on the QR screen (C-03), via the manual-entry icon. | H62: none | I62: — | J62: — | K62: C-02, C-03 | L62: A-19, C-05 | M62: Q-68, Q-75 | N62: Yes (2) | O62: Full | P62: feature-docs/en/40-checker-app/C-04-manual-entry.md | Q62: Not reviewed
B63: Checker App | C63: Gate Operations & Checking | D63: C-05 | E63: Scan sync | F63: Upload local scans and receive other devices' scans every 90 seconds. | G63: Automatic, on the QR screen (C-03). Route /qrPage. | H63: TicketChecker | I63: 2 | J63: POST /ticketChecker/api/v1/tickets/sync-tickets | K63: C-02, C-03, C-04 | L63: A-19, S-14 | M63: Q-76 | N63: Yes (1) | O63: Full | P63: feature-docs/en/40-checker-app/C-05-ticket-sync.md | Q63: Not reviewed
B64: Checker App | C64: Gate Operations & Checking | D64: C-06 | E64: Signature-only ticket validation | F64: Check a QR's signature without gate/event rules or recording an entry. | G64: A checker or a support engineer, route /manualTicketValidation. | H64: none | I64: — | J64: — (Method channel) | K64: C-03 | L64: nothing — it is read-only by design. | M64: Q-77 | N64: Yes (1) | O64: Full on Android; always fails on iOS | P64: feature-docs/en/40-checker-app/C-06-manual-ticket-validation.md | Q64: Not reviewed
B65: System-Initiated | C65: Venues & Seating | D65: S-01 | E65: Level capacity update (OrderSuccess queue) | F65: Apply booked/released seats to level capacity after order events. | G65: - Producer (user order): Booking, when a payment is confirmed: DgePay callback HandleDgePayment, the re-check job RevaildateRecentPendingBookingsAsync (S-05), and the handler behind the anonymous GET payment-status-bypa… | H65: Booking | I65: — | J65: — | K65: A-07, P-06 | L65: P-04, S-02, S-04 | M65: Q-09, Q-10 | N65: Yes (1) | O65: Full | P65: feature-docs/en/50-system-initiated/S-01-level-capacity-update.md | Q65: Not reviewed
B66: System-Initiated | C66: Venues & Seating | D66: S-02 | E66: Event live capacity (EventCapacity queue) | F66: Recompute an event's live capacity after capacity changes. | G66: Producer: Booking CapacityManager.BookLevelCapacity, on every call, for both user orders (at order creation) and admin… · Consumer: Booking service worker; no user, no token. | H66: Booking | I66: 1 | J66: — | K66: A-07, S-01 | L66: P-02, S-04 | M66: Q-09 | N66: — | O66: Full | P66: feature-docs/en/50-system-initiated/S-02-event-live-capacity.md | Q66: Not reviewed
B67: System-Initiated | C67: Venues & Seating | D67: S-03 | E67: Locked-capacity refresh | F67: Release seats locked by unpaid orders after they expire. | G67: - Producer of work: CapacityManager.BookLevelCapacity adds a key to the Redis set refresh when the level's live capacity is 0 after the booking step. | H67: Booking | I67: — | J67: — | K67: S-01 | L67: P-04 | M67: Q-10 | N67: Yes (1) | O67: Full | P67: feature-docs/en/50-system-initiated/S-03-locked-capacity-refresh.md | Q67: Not reviewed
B68: System-Initiated | C68: Venues & Seating | D68: S-04 | E68: Scheduler capacity reconcile | F68: Periodic capacity reconciliation triggered from the Scheduler service. | G68: A timer in the Scheduler service (CapacityUpdateService); no user, no token. | H68: Scheduler | I68: — | J68: — | K68: S-01, S-02 | L68: P-02 | M68: — | N68: — | O68: Full | P68: feature-docs/en/50-system-initiated/S-04-scheduler-capacity-update.md | Q68: Not reviewed
B69: System-Initiated | C69: Bookings & Payments | D69: S-05 | E69: Pending/failed payment revalidation | F69: Re-check unfinished payments with DgePay and update order status. | G69: Timer in the Scheduler (PendingOrFailedBookingStatusUpdateService); calls Booking PUT /booking/api/v1/user-booking-order/update-status without a token [HTTP, no token / internal]. | H69: Scheduler | I69: 1 | J69: — | K69: P-06 | L69: P-07, S-01, S-06 | M69: Q-11 | N69: — | O69: Partial | P69: feature-docs/en/50-system-initiated/S-05-pending-failed-revalidation.md | Q69: Not reviewed
B70: System-Initiated | C70: Bookings & Payments | D70: S-06 | E70: Booking status → Generated | F70: Mark orders Generated once all their tickets exist. | G70: Timer in the Booking service (BookingStatusUpdateService); calls Ticketing over HTTP without a token [HTTP, no token / internal]. | H70: Ticketing | I70: 1 | J70: — | K70: S-07, S-08 | L70: P-07, S-10, S-12 | M70: Q-06, Q-12 | N70: — | O70: Partial | P70: feature-docs/en/50-system-initiated/S-06-booking-status-generated.md | Q70: Not reviewed
B71: System-Initiated | C71: Ticketing | D71: S-07 | E71: Initiate user ticket generation | F71: Start ticket generation for paid orders that requested it. | G71: Timer in the Booking service (InitiateUserTicketGenerationService). | H71: Booking | I71: 3 | J71: — | K71: A-08, A-13, P-06, S-05 | L71: P-07, P-09, S-06, S-08 | M71: Q-12 | N71: — | O71: Partial | P71: feature-docs/en/50-system-initiated/S-07-initiate-user-ticket-generation.md | Q71: Not reviewed
B72: System-Initiated | C72: Ticketing | D72: S-08 | E72: Ticket signing via TSP (TicketSigning queue) | F72: Digitally sign ticket PDFs through the TSP and store them in S3. | G72: - Producers: Ticketing TicketManager: user tickets (S-07 and the customer button, TicketGenerateRequest) and reserved tickets (PublishBulkTicketToSign, CreateReservationTicketsAsync; A-12). | H72: Ticketing | I72: — | J72: — | K72: A-13, S-07 | L72: C-03, P-09, S-06, S-09 | M72: Q-09, Q-13 | N72: — | O72: Partial / not locally for the real sign… | P72: feature-docs/en/50-system-initiated/S-08-ticket-signing.md | Q72: Not reviewed
B73: System-Initiated | C73: Ticketing | D73: S-09 | E73: Reserved ticket merge/zip (TicketProcessing queue) | F73: Merge or zip a reservation's signed tickets in the Utility service. | G73: Producer: an admin (admin pool) through Ticketing GET /ticketing/api/v1/booking-order-ticket/merge-reserved?reservation… · Consumer: Utility service worker; no user, no token. Utility is the only service whose main job is this worker. | H73: Utility | I73: 5 | J73: — | K73: A-11, A-12, S-08 | L73: X-20 | M73: Q-06, Q-09, Q-14 | N73: Yes (1) | O73: Partial | P73: feature-docs/en/50-system-initiated/S-09-ticket-merge-zip.md | Q73: Not reviewed
B74: System-Initiated | C74: Bookings & Payments | D74: S-10 | E74: VAT challan with NBR (VatChallanProcessing queue) | F74: Record VAT for paid orders and download the challan from NBR. | G74: Producer: Booking UserBookingOrderManager.HandleDgePayment (the DgePay callback) publishes one message when the payment… · Consumer: Booking worker; no user, no token. | H74: Scheduler | I74: 3 | J74: — | K74: P-06 | L74: A-22, P-07 | M74: Q-06, Q-09, Q-15 | N74: — | O74: Partial | P74: feature-docs/en/50-system-initiated/S-10-vat-challan.md | Q74: Not reviewed
B75: System-Initiated | C75: Notifications | D75: S-11 | E75: Push delivery to FCM (FirebaseNotification queue) | F75: Deliver queued push messages through Firebase Cloud Messaging. | G75: Producer: PushNotification NotificationManager (after Admin calls send-to-all on event publish, A-07). · Consumer: Scheduler FirebaseNotificationService; no user, no token, no lock. | H75: Scheduler | I75: — | J75: — | K75: U-09, X-23 | L75: U-10 | M75: — | N75: — | O75: Partial / not locally for delivery | P75: feature-docs/en/50-system-initiated/S-11-firebase-notification.md | Q75: Not reviewed
B76: System-Initiated | C76: Notifications | D76: S-12 | E76: Ticket-generated notification | F76: Tell customers their tickets are ready. | G76: Timer in the Scheduler service (SendNotificationAfterGeneratedTicketService). | H76: Scheduler | I76: 3 | J76: — | K76: S-06, S-08 | L76: P-07 | M76: Q-05 | N76: — | O76: Partial | P76: feature-docs/en/50-system-initiated/S-12-ticket-generated-notification.md | Q76: Not reviewed
B77: System-Initiated | C77: Notifications | D77: S-13 | E77: Device-token cleanup | F77: Daily removal of stale device tokens. | G77: Timer in the Scheduler service (DeviceTokenCleanupService); no user. | H77: Scheduler | I77: 1 | J77: — | K77: U-09 | L77: S-11 | M77: Q-16 | N77: — | O77: Partial | P77: feature-docs/en/50-system-initiated/S-13-device-token-cleanup.md | Q77: Not reviewed
B78: System-Initiated | C78: Gate Operations & Checking | D78: S-14 | E78: Checked-ticket sync (Redis → database) | F78: Persist gate scans collected in Redis to the database. | G78: Timer in the Admin service (CheckedTicketService); no user. | H78: Admin | I78: — | J78: — | K78: A-18, C-05 | L78: A-19 | M78: Q-17 | N78: Yes (1) | O78: Full for the worker; the checker app ca… | P78: feature-docs/en/50-system-initiated/S-14-checked-ticket-sync.md | Q78: Not reviewed
B79: System-Initiated | C79: Gate Operations & Checking | D79: S-15 | E79: Gate download-status cleanup | F79: Reset checker download flags on a schedule. | G79: Timer in the Admin service (GateCheckerDownloadStatusCleanupService); no user, no HTTP calls. | H79: Admin | I79: — | J79: — | K79: A-07, A-18 | L79: C-02 | M79: — | N79: — | O79: Full | P79: feature-docs/en/50-system-initiated/S-15-gate-download-status-cleanup.md | Q79: Not reviewed
B80: System-Initiated | C80: Pricing & Promotions | D80: S-16 | E80: Promo-code status update | F80: Activate/expire promo codes by their dates. | G80: Timer in the Admin service (PromoCodeStatusUpdateService); no user. | H80: Admin | I80: 1 | J80: — | K80: A-15, P-06 | L80: A-15, P-05 | M80: Q-02, Q-18 | N80: — | O80: Full | P80: feature-docs/en/50-system-initiated/S-16-promo-code-status.md | Q80: Not reviewed
B81: System-Initiated | C81: Pricing & Promotions | D81: S-17 | E81: System-discount status update | F81: Activate/expire system discounts by their dates. | G81: Timer in the Admin service (SystemDiscountStatusUpdateService); no user, no HTTP calls. | H81: Admin | I81: — | J81: — | K81: A-16 | L81: A-22, P-06, S-10 | M81: Q-02 | N81: — | O81: Full | P81: feature-docs/en/50-system-initiated/S-17-discount-status.md | Q81: Not reviewed
B82: Cross-Cutting | C82: Auth & Security | D82: X-01 | E82: Admin login (phone OTP + password) | F82: Three-step admin sign-in: phone, SMS OTP, Cognito password. | G82: Staff member with an account in the Admin Cognito pool (created by X-05) | H82: Cognito + Serverless API | I82: 3 | J82: — | K82: X-05 | L82: A-12, X-04, X-17 | M82: Q-03 | N82: — | O82: Partial | P82: feature-docs/en/60-cross-cutting/X-01-admin-login.md | Q82: Not reviewed
B83: Cross-Cutting | C83: Auth & Security | D83: X-02 | E83: Admin forgot password | F83: Reset an admin password after an SMS OTP. | G83: Staff member with an Admin-pool account, not signed in | H83: Cognito + notification | I83: 3 | J83: — | K83: X-05 | L83: X-01 | M83: Q-04, Q-05 | N83: — | O83: Partial | P83: feature-docs/en/60-cross-cutting/X-02-admin-forgot-password.md | Q83: Not reviewed
B84: Cross-Cutting | C84: Auth & Security | D84: X-03 | E84: Admin change password and logout | F84: Change the password in Cognito; sign out and clear local state. | G84: Any signed-in admin-portal user | H84: Admin | I84: — | J84: — | K84: X-01 | L84: A-01, X-04 | M84: — | N84: — | O84: Full | P84: feature-docs/en/60-cross-cutting/X-03-admin-change-password-logout.md | Q84: Not reviewed
B85: Cross-Cutting | C85: Auth & Security | D85: X-04 | E85: Admin session handling (token attach and refresh) | F85: How the admin portal attaches, caches and refreshes tokens. | G85: Any signed-in admin-portal user; triggered by every HTTP call the portal makes | H85: Admin, Cognito | I85: — | J85: — | K85: A-01, X-01 | L85: every A-xx feature. | M85: — | N85: — | O85: Full | P85: feature-docs/en/60-cross-cutting/X-04-admin-session.md | Q85: Not reviewed
B86: Cross-Cutting | C86: Users & Accounts | D86: X-05 | E86: Staff account provisioning | F86: How admin, checker and agent accounts are created in Cognito by the Admin service. | G86: Admin-portal user in the global menu (program 0). Admin accounts: role admin. Checker accounts: admin, event_manager, ticket_manager, ticket_operator (controller roles). Agent accounts: no server-side restriction (see notes) | H86: Admin, Cognito | I86: 9 | J86: — | K86: X-01 | L86: A-18, X-01, X-12, X-13, X-15, X-16 | M86: Q-04, Q-05 | N86: — | O86: Partial | P86: feature-docs/en/60-cross-cutting/X-05-admin-provisioning.md | Q86: Not reviewed
B87: Cross-Cutting | C87: Users & Accounts | D87: X-06 | E87: Customer registration | F87: Sign-up with email and phone OTP, then password; OneID alternative. | G87: Anonymous visitor | H87: Identity API | I87: 4 | J87: — | K87: identity API, Cognito User pool. | L87: P-11, X-07, X-08 | M87: Q-01 | N87: — | O87: Not locally | P87: feature-docs/en/60-cross-cutting/X-06-user-registration.md | Q87: Not reviewed
B88: Cross-Cutting | C88: Auth & Security | D88: X-07 | E88: Customer login with phone and password | F88: User-pool sign-in in portal and app. | G88: Customer with a User-pool account (X-06) | H88: Identity API, Cognito | I88: 1 | J88: — | K88: X-06 | L88: P-05, P-06, P-07 | M88: Q-01, Q-03 | N88: — | O88: Full in the portal, Not locally in the… | P88: feature-docs/en/60-cross-cutting/X-07-user-password-login.md | Q88: Not reviewed
B89: Cross-Cutting | C89: Auth & Security | D89: X-08 | E89: OneID single sign-on | F89: Sign in through OneID federated by Cognito; auto-register on first login. | G89: Customer with a OneID account | H89: Identity API, OneID | I89: 4 | J89: — | K89: Cognito User pool with provider oneid, OneID, identity API. | L89: P-10, X-07 | M89: Q-01 | N89: — | O89: Partial (portal only) | P89: feature-docs/en/60-cross-cutting/X-08-oneid-sso.md | Q89: Not reviewed
B90: Cross-Cutting | C90: Auth & Security | D90: X-09 | E90: Customer forgot/reset password | F90: OTP-based password reset through the identity API. | G90: Customer, not signed in | H90: Identity API | I90: 2 | J90: — | K90: X-06 | L90: X-07 | M90: Q-01 | N90: — | O90: Not locally | P90: feature-docs/en/60-cross-cutting/X-09-user-forgot-password.md | Q90: Not reviewed
B91: Cross-Cutting | C91: Auth & Security | D91: X-10 | E91: Customer change password, logout and token attach | F91: Session handling in portal and app. | G91: Signed-in customer | H91: Cognito, identity API | I91: — | J91: — | K91: X-07, X-08 | L91: all token-protected P-xx and U-xx features. | M91: — | N91: — | O91: Full in the portal, Not locally in the… | P91: feature-docs/en/60-cross-cutting/X-10-user-session.md | Q91: Not reviewed
B92: Cross-Cutting | C92: Users & Accounts | D92: X-11 | E92: Delete account and app force-update | F92: App-only account deletion and the minimum-version gate. | G92: Customer (delete account, force update); gate staff (force update in the checker app) | H92: Identity API | I92: 2 | J92: — | K92: X-07 | L92: U-01, U-07 | M92: Q-01 | N92: — | O92: Not locally | P92: feature-docs/en/60-cross-cutting/X-11-delete-account-force-update.md | Q92: Not reviewed
B93: Cross-Cutting | C93: Auth & Security | D93: X-12 | E93: Checker login | F93: TicketChecker-pool sign-in in the checker app. | G93: Gate staff (ticket checker) | H93: Cognito | I93: 1 | J93: — | K93: A-17, A-18, X-05 | L93: all C-xx features. | M93: Q-01 | N93: — | O93: Not locally (sign-in), Partial (backend) | P93: feature-docs/en/60-cross-cutting/X-12-checker-login.md | Q93: Not reviewed
B94: Cross-Cutting | C94: Users & Accounts | D94: X-13 | E94: Agent pool and offline-sold tickets | F94: Agent accounts and the only Agent API. | G94: Seller agent (account created in the admin portal, A-26) | H94: Ticketing, Cognito | I94: 1 | J94: — | K94: A-11, A-12, A-26 | L94: nothing that reads it back (see notes). | M94: Q-07 | N94: — | O94: Partial | P94: feature-docs/en/60-cross-cutting/X-13-agent-pool.md | Q94: Not reviewed
B95: Cross-Cutting | C95: Auth & Security | D95: X-14 | E95: Authorization layer 1: pool schemes and policies | F95: Which Cognito pool a token must come from, per endpoint. | G95: Every API request with an Authorization: Bearer … header, in every service that calls AddJwtBearerAuthentication and UseAuthentication (all except Platform, PushNotification and UserAuth, where UseAuthentication/UseAuth… | H95: all services | I95: — | J95: — | K95: X-26 | L95: every token-protected feature. | M95: — | N95: — | O95: Full | P95: feature-docs/en/60-cross-cutting/X-14-authz-pool-policies.md | Q95: Not reviewed
B96: Cross-Cutting | C96: Auth & Security | D96: X-15 | E96: Authorization layers 2–3: staff roles | F96: custom:role → role claims and [Authorize(Roles=…)]; role × endpoint matrix. | G96: Every request with an Admin-pool token to the Admin or UserIssue service. | H96: all services | I96: — | J96: — | K96: X-05, X-14, X-25 | L96: X-16 | M96: — | N96: — | O96: Full | P96: feature-docs/en/60-cross-cutting/X-15-authz-roles.md | Q96: Not reviewed
B97: Cross-Cutting | C97: Auth & Security | D97: X-16 | E97: Authorization layer 4: program scope | F97: X-Program-Id, custom:program_ids, [AuthorizeProgram] and the EF query filter. | G97: Admin-portal users after choosing a program (A-01) | H97: all services | I97: — | J97: — | K97: A-01, X-15 | L97: A-21 | M97: — | N97: — | O97: Full | P97: feature-docs/en/60-cross-cutting/X-16-authz-program-scope.md | Q97: Not reviewed
B98: Cross-Cutting | C98: Auth & Security | D98: X-17 | E98: Client-side authorization (menus and guards) | F98: What the portals hide or block per role; not a security boundary. | G98: Admin-portal staff; user-portal customers | H98: portals | I98: — | J98: — | K98: A-01, X-01 | L98: what each role can reach in the UI for every A-xx feature. | M98: — | N98: — | O98: Full | P98: feature-docs/en/60-cross-cutting/X-17-authz-client-side.md | Q98: Not reviewed
B99: Cross-Cutting | C99: Auth & Security | D99: X-18 | E99: Endpoints without authorization | F99: Every endpoint reachable without a token, and why. | G99: Any HTTP client that can reach the service. | H99: several | I99: — | J99: — | K99: network exposure (architecture Q1b). | L99: A-08, A-10, A-11, A-14, A-21, A-22, A-26, X-02 | M99: Q-04 | N99: — | O99: Full | P99: feature-docs/en/60-cross-cutting/X-18-endpoints-without-auth.md | Q99: Not reviewed
B100: Cross-Cutting | C100: Platform & Infrastructure | D100: X-19 | E100: Service-to-service communication | F100: Typed HTTP clients with token forwarding, tokenless worker calls, and SQS. | G100: A controller action (user request) or a background worker that needs data or work from another service or an external system. | H100: all | I100: — | J100: — | K100: X-26 | L100: every multi-service feature. | M100: Q-01 | N100: — | O100: Full | P100: feature-docs/en/60-cross-cutting/X-19-service-to-service.md | Q100: Not reviewed
B101: Cross-Cutting | C101: Platform & Infrastructure | D101: X-20 | E101: File storage (S3, CloudFront) | F101: Media and ticket buckets, folder layout, signed URLs and cookies. | G101: - Admin portal users uploading images or ticket layouts (admin pool). | H101: all | I101: 3 | J101: — | K101: X-01, X-26 | L101: event, program, team, venue, ticket-layout and reserved-tic… | M101: Q-06 | N101: — | O101: Partial | P101: feature-docs/en/60-cross-cutting/X-20-file-storage.md | Q101: Not reviewed
B102: Cross-Cutting | C102: Notifications | D102: X-21 | E102: Email (SES) | F102: Where the platform sends email. | G102: An admin-portal user (admin pool policy) chooses reserved tickets and clicks *Send* (A-12). | H102: Ticketing | I102: 1 | J102: — | K102: A-12, S-08 | L102: nothing downstream. | M102: Q-06 | N102: — | O102: Partial | P102: feature-docs/en/60-cross-cutting/X-21-email-ses.md | Q102: Not reviewed
B103: Cross-Cutting | C103: Notifications | D103: X-22 | E103: SMS and the external notification service | F103: SMS/OTP and notification calls to services outside the repos. | G103: | Message | Triggered by | Actor | |---|---|---| | SMS "account created" with user name and password | Admin creates an admin, agent or checker user (X-05) | Admin user | | SMS "password changed" with the new password |… | H103: external service | I103: 3 | J103: — | K103: S-07, S-08, X-05 | L103: staff onboarding, customer ticket-ready message. | M103: Q-03, Q-05 | N103: — | O103: Not locally | P103: feature-docs/en/60-cross-cutting/X-22-sms-notification.md | Q103: Not reviewed
B104: Cross-Cutting | C104: Notifications | D104: X-23 | E104: Push notifications (PushNotification service, Firebase) | F104: Device tokens, send APIs, queue and FCM. | G104: - Register, replace, delete a token: the user app, on start-up and token refresh (U-09). | H104: PushNotification, Scheduler | I104: 9 | J104: — | K104: A-07, U-09 | L104: U-10 | M104: Q-04, Q-08, Q-16 | N104: — | O104: Partial | P104: feature-docs/en/60-cross-cutting/X-23-push-firebase.md | Q104: Not reviewed
B105: Cross-Cutting | C105: Auth & Security | D105: X-24 | E105: Activity logging (audit trail) | F105: How entity changes are recorded across services. | G105: Any SaveChanges in Admin, Booking, Event, Ticketing, TicketChecker or UserIssue. | H105: all | I105: 3 | J105: — | K105: X-01, X-15 | L105: A-27 | M105: Q-02 | N105: — | O105: Full | P105: feature-docs/en/60-cross-cutting/X-24-activity-logging.md | Q105: Not reviewed
B106: Cross-Cutting | C106: Platform & Infrastructure | D106: X-25 | E106: Redis: cache, live capacity and locks | F106: Key families, cache usage and RedLock distributed locks. | G106: Any request or worker in Admin, Booking, Event, Ticketing, TicketChecker, Scheduler, UserIssue and Utility. | H106: all | I106: — | J106: — | K106: X-26 | L106: A-10, P-04, P-06 | M106: Q-02 | N106: — | O106: Full | P106: feature-docs/en/60-cross-cutting/X-25-redis.md | Q106: Not reviewed
B107: Cross-Cutting | C107: Platform & Infrastructure | D107: X-26 | E107: Configuration and secrets | F107: Where settings come from in AWS and locally; key reference. | G107: A developer starting a service locally, or CodeBuild building and deploying an environment. | H107: all | I107: — | J107: — | K107: nothing. | L107: every feature. | M107: Q-02, Q-06 | N107: — | O107: Full | P107: feature-docs/en/60-cross-cutting/X-26-configuration.md | Q107: Not reviewed

Sheet Open Queries
B2: Open Queries — 75 items for the BS-23 review
B3: From 99-open-queries.md. Every [UNCONFIRMED: Q-nn] marker in the docs points here. Kinds: External (BS23 answers), Deployment (BS23/infra), Ambiguity (BS23/business), Defect (RVL fixes).
B4: Q-ID | C4: Kind | D4: Question / finding | E4: Why it is open (evidence) | F4: Cited features | G4: BS-23 response | H4: Status | I4: Answered by | J4: Date
B5: Q-01 | C5: External | D5: Where is the identity API source, who hosts it, and who owns it? | E5: Registration, OTP, my-profile, register-sso, allowed-app-version and delete-my-profile all go to an API that is in none of the five repositories. Locally it is http://localhost:4200/ (scripts/user-secrets.example.json). Ask BS23 for its repository, hosting and owner before go-live. | F5: P-11, U-01, U-07, X-06, X-07, X-08, X-09, X-11 | H5: Open
B6: Q-02 | C6: Deployment | D6: Is production one PostgreSQL database on schema etp, or one database per service? | E6: Every DbContext uses schema etp but each service has its own connection string. The architecture document says "one schema per service"; the code says one schema for all. This decides whether the cross-service table reads (S-17, X-24) can work at all. | F6: X-24, X-26 | H6: Open
B7: Q-03 | C7: External | D7: Where is the Serverless / Lambda identity API source? | E7: Used by Admin login to look up user names and phones by id, and by the Booking flow. Not in any repository. | F7: X-01, X-07 | H7: Open
B8: Q-04 | C8: Deployment | D8: Does the ingress or WAF expose routes that the services leave unauthenticated? | E8: PushNotification has its authentication middleware commented out, the user-issue chat REST controller has no [Authorize], and the gateway path for the admin generate-signed-token matters. Whether these are reachable from the internet is a deployment fact. This is the single most important deployment question in the handover — see X-18. | F8: P-01, X-02, X-05, X-18, X-23 | H8: Open
B9: Q-05 | C9: External | D9: Where is the external notification service source and what does it do with the payload? | E9: The backend posts JSON to Notification:Endpoint for every SMS. The text, the channel and the templating all live there — so the platform cannot tell you what a customer actually receives. | F9: S-12, X-05, X-22 | H9: Open
B10: Q-06 | C10: External | D10: Are the dummy external integrations still dummies in production? | E10: OneID, TSP (ticket signing) and NBR VAT are stubbed locally to https://*.invalid. Ticket signing, the OneID ticket sync and the VAT challan therefore cannot be tested end-to-end locally, and it is not visible from the code whether the real integrations are wired in a deployed environment. | F10: P-10, S-06, S-09, S-10, X-20, X-21, X-26 | H10: Open
B11: Q-07 | C11: External | D11: Is there an agent app or client for the Agent Cognito pool? | E11: Agent accounts, the Agent-policy endpoint POST /ticketing/api/v1/offline-sold-ticket, and the OfflineSoldTickets data all exist, but no client in the five repositories uses them and nothing reads the offline-sold tickets back. Either a client is missing from the handover, or the feature is dormant. | F11: A-26, X-13 | H11: Open
B12: Q-08 | C12: Deployment | D12: Should the push send methods on PushNotification be live? | E12: send-to-users and send-to-user exist on the service and in the Admin client but have no caller in the five repositories. The only live sender is event publish. Dead code or a missing feature — ask which. | F12: X-23 | H12: Open
B13: Q-09 | C13: Ambiguity | D13: What is the intended retry and dead-letter policy for the SQS consumers? | E13: RetryCount is incremented on the deserialised copy only and the message is not re-published with it, so MAX_RETRY_COUNT = 3 is never reached and a permanently failing message is retried for ever at the queue's visibility timeout. No dead-letter handling is visible in code for any consumer. | F13: S-01, S-02, S-08, S-09, S-10 | H13: Open
B14: Q-10 | C14: Defect | D14: Key mismatch in the payment-bypass handler. On Failed, HandleDgePaymentBypass deletes from level_locked_{EventId}_… (underscore, public event id) while everything else uses level_locked:{EventLongId}_…, so the entry is not removed and only lapses by the 12-minute rule. | E14: S-01 | F14: S-01 | H14: Open
B15: Q-11 | C15: Ambiguity | D15: Is a paid-but-late order reconciled, or silently lost? | E15: CancelBookingAsync asks DgePay and discards the answer, cancelling every Pending/Failed order older than 12 minutes. A customer who paid after the 7–10 minute check window can end with money taken and an order cancelled. Whether anyone reconciles this by hand is not visible. | F15: P-06, S-05 | H15: Open
B16: Q-12 | C16: Ambiguity | D16: What happens to an order stuck in Requested? | E16: There is no timeout, no alert and no dead-letter for orders whose tickets never complete signing. Support finds them in the reconciliation screen. | F16: P-08, S-06, S-07 | H16: Open
... B79: Q-77 | C79: Defect | D79: Is /manualTicketValidation intended for admissions? It proves authenticity only — not event, not gate, not already-used. Anyone using it to admit customers would admit a used or wrong-gate ticket. It should be labelled as a diagnostic tool in the UI. | E79: C-06 | F79: C-06 | H79: Open

Sheet Traceability
B2: Technical Traceability — feature → service, endpoint, state
B3: From 02-traceability-matrix.md (§2, §3, §4). For DEV/OPS: where each feature's behaviour lives.
B4: ID | C4: Feature | D4: Area | E4: Service(s) | F4: Also touches / trigger | G4: Primary endpoint | H4: Auth | I4: Queues | J4: Redis keys | K4: Local state | L4: External systems
B5: A-01 | C5: Program selection and program-scoped menu | D5: Admin Portal | E5: Admin | F5: Cognito (session), localStorage | G5: GET /admin/api/v1/program | H5: admin | I5: — | J5: — | K5: localStorage globalProgramId | L5: —
B6: A-02 | C6: Programs | D6: Admin Portal | E6: Admin | F6: Cognito | G6: POST /admin/api/v1/program | H6: admin | I6: — | J6: — | K6: — | L6: —
B7: A-03 | C7: Program settings | D7: Admin Portal | E7: Admin | F7: — | G7: /admin/api/v1/program-settings | H7: admin | I7: — | J7: — | K7: — | L7: —
B8: A-04 | C8: Teams | D8: Admin Portal | E8: Admin | F8: — | G8: /admin/api/v1/teams | H8: admin | I8: — | J8: — | K8: — | L8: —
B9: A-05 | C9: Venues and stadium layout | D9: Admin Portal | E9: Admin | F9: S3 (venue media) | G9: /admin/api/v1/venues | H9: admin | I9: — | J9: — | K9: — | L9: S3 / CloudFront
B10: A-06 | C10: Program–venue mapping and venue details | D10: Admin Portal | E10: Admin | F10: — | G10: /admin/api/v1/programVenueDetails | H10: admin | I10: — | J10: — | K10: — | L10: —
B11: A-07 | C11: Events (matches) | D11: Admin Portal | E11: Admin | F11: — | G11: /admin/api/v1/events | H11: admin | I11: — | J11: — | K11: — | L11: —
B12: A-08 | C12: Event settings override | D12: Admin Portal | E12: Admin | F12: — | G12: /admin/api/v1/event-settings | H12: admin | I12: — | J12: — | K12: — | L12: —
B13: A-09 | C13: Event venue details and per-level pricing | D13: Admin Portal | E13: Admin | F13: — | G13: /admin/api/v1/eventsVenueDetails | H13: admin | I13: — | J13: — | K13: — | L13: —
B14: A-10 | C14: Event capacity adjustment | D14: Admin Portal | E14: Booking | F14: Redis | G14: /booking/api/v1/event-capacity-adjustment | H14: admin | I14: — | J14: capacity/*, capacityAction | K14: — | L14: —
B15: A-11 | C15: Seat reservation (complimentary / partner) | D15: Admin Portal | E15: Booking | F15: — | G15: /booking/api/v1/seat-reservation | H15: admin | I15: — | J15: — | K15: — | L15: —
... B107: X-26 | C107: Configuration and secrets | D107: Cross-Cutting | E107: all | F107: Q-07 | G107: — | H107: — | I107: — | J107: — | K107: — | L107: —

Sheet Gap Log
B2: Gap Log — anything the documentation missed
B3: For the BS-23 review: record features or behaviours that exist in the product but not in the feature docs (or vice versa). Add rows as needed.
B4: Area | C4: Proposed missing feature / gap | D4: Why we think it is missing | E4: Where seen (screen, endpoint, doc) | F4: Raised by | G4: Date | H4: BS-23 response

Sheet Review
B2: Review — workbook integrity self-checks (live formulas)
B4: Check | C4: Expected | D4: Actual | E4: Status
B5: Feature rows in Feature Matrix | C5: 103 | D5: =COUNTA('Feature Matrix'!D5:D107) -> 103 | E5: =IF(C5=D5,"PASS","FAIL") -> PASS
B6: Open-query rows in Open Queries | C6: 75 | D6: =COUNTA('Open Queries'!B5:B79) -> 75 | E6: =IF(C6=D6,"PASS","FAIL") -> PASS
B7: Every feature has a BS-23 status | C7: 103 | D7: =COUNTA('Feature Matrix'!Q5:Q107) -> 103 | E7: =IF(C7=D7,"PASS","FAIL") -> PASS
B8: Every query has a status | C8: 75 | D8: =COUNTA('Open Queries'!H5:H79) -> 75 | E8: =IF(C8=D8,"PASS","FAIL") -> PASS
B9: Summary area totals equal feature rows | C9: 103 | D9: =Summary!C12 -> 103 | E9: =IF(C9=D9,"PASS","FAIL") -> PASS
B10: Summary query total equals query rows | C10: 75 | D10: =Summary!C21 -> 75 | E10: =IF(C10=D10,"PASS","FAIL") -> PASS
